pureskillgg_assistant_coach/__init__.py
pureskillgg_assistant_coach/department/__init__.py
pureskillgg_assistant_coach/department/attach_content_to_assignment.py
pureskillgg_assistant_coach/department/breakdown.py
pureskillgg_assistant_coach/department/model.py
pureskillgg_assistant_coach/department/model_test.py
pureskillgg_assistant_coach/department/reader_fs.py
pureskillgg_assistant_coach/department/reader_s3.py
pureskillgg_assistant_coach/department/resource.py
pureskillgg_assistant_coach/department/snapshots/__init__.py
pureskillgg_assistant_coach/department/snapshots/snap_model_test.py
pureskillgg_assistant_coach/department/tag_matching_test.py
pureskillgg_assistant_coach/department/translation.py
pureskillgg_assistant_coach-1.1.1.dist-info/LICENSE.txt
pureskillgg_assistant_coach-1.1.1.dist-info/METADATA
pureskillgg_assistant_coach-1.1.1.dist-info/WHEEL
pureskillgg_assistant_coach-1.1.1.dist-info/RECORD
