Metadata-Version: 2.1
Name: pureskillgg-assistant-coach
Version: 1.1.1
Summary: Shared Python modules to assist coaching services.
Home-page: https://github.com/pureskillgg/assistant-coach
License: SEE LICENSE IN LICENSE.txt
Author: PureSkill.gg
Author-email: secure@pureskill.gg
Requires-Python: >=3.9,<4.0
Classifier: License :: Other/Proprietary License
Classifier: Programming Language :: Python :: 3
Classifier: Programming Language :: Python :: 3.9
Classifier: Programming Language :: Python :: 3.10
Classifier: Programming Language :: Python :: 3.11
Requires-Dist: boto3 (>=1.12.32,<2.0.0)
Requires-Dist: pybars3 (>=0.9.7,<0.10.0)
Requires-Dist: python-rapidjson (>=1.0.0,<2.0.0)
Project-URL: Repository, https://github.com/pureskillgg/assistant-coach
